django_north/__init__.py
django_north/management/__init__.py
django_north/management/contenttypes.py
django_north/management/migrations.py
django_north/management/permissions.py
django_north/management/commands/__init__.py
django_north/management/commands/flush.py
django_north/management/commands/makemigrations.py
django_north/management/commands/migrate.py
django_north/management/commands/runserver.py
django_north/management/commands/showfixtures.py
django_north/management/commands/showmigrations.py
django_north/management/commands/sqlall.py
django_north/management/commands/sqlmigrate.py
django_north/management/commands/squashmigrations.py
django_north-0.3.2.dist-info/AUTHORS.rst
django_north-0.3.2.dist-info/LICENSE
django_north-0.3.2.dist-info/METADATA
django_north-0.3.2.dist-info/WHEEL
django_north-0.3.2.dist-info/top_level.txt
django_north-0.3.2.dist-info/RECORD
