Metadata-Version: 2.1
Name: django-north
Version: 0.3.2
Summary: Yet another way to manage migrations: DBA as a service
Home-page: https://github.com/peopledoc/django-north
Author: Lauréline Guérin
Author-email: laureline.guerin@people-doc.com
License: MIT
Keywords: django-north
Platform: UNKNOWN
Classifier: Development Status :: 4 - Beta
Classifier: Framework :: Django
Classifier: Framework :: Django :: 1.11
Classifier: Framework :: Django :: 2.0
Classifier: Framework :: Django :: 2.1
Classifier: Framework :: Django :: 2.2
Classifier: Intended Audience :: Developers
Classifier: License :: OSI Approved :: BSD License
Classifier: Natural Language :: English
Classifier: Programming Language :: Python :: 3.6
Classifier: Programming Language :: Python :: 3.7
Requires-Dist: Django (>=1.11)
Requires-Dist: septentrion[psycopg2] (>=0.6.1)
